yadet/__init__.py
yadet/batch/__init__.py
yadet/batch/batch_run.py
yadet/config/__init__.py
yadet/config/project.py
yadet/config/table.py
yadet/engine/__init__.py
yadet/engine/source/__init__.py
yadet/engine/source/base.py
yadet/engine/source/mssql.py
yadet/engine/target/__init__.py
yadet/engine/target/base.py
yadet/engine/target/file_system.py
yadet/errors/__init__.py
yadet/helpers/__init__.py
yadet/helpers/base.py
yadet/helpers/json.py
yadet/helpers/parser.py
yadet/helpers/sql.py
yadet/interface/__init__.py
yadet/interface/extract_transfer.py
yadet/interface/source.py
yadet/interface/target.py
yadet/objects/__init__.py
yadet/objects/base.py
yadet-1.6.0.dist-info/licenses/LICENSE
yadet-1.6.0.dist-info/METADATA
yadet-1.6.0.dist-info/WHEEL
yadet-1.6.0.dist-info/top_level.txt
yadet-1.6.0.dist-info/zip-safe
yadet-1.6.0.dist-info/RECORD
