Metadata-Version: 2.4
Name: yadet
Version: 1.6.0
Summary: A simple and effective Python data extraction tool for getting batch data exports and store in a simple format.
Home-page: https://github.com/robbitt07/yadet
Author: Robert Goss
Author-email: Robert Goss <robertgoss07@gmail.com>
License: MIT License
Project-URL: Homepage, https://github.com/robbitt07/yadet
Project-URL: Bug Tracker, https://github.com/robbitt07/yadet/issues
Classifier: Programming Language :: Python :: 3
Classifier: License :: OSI Approved :: MIT License
Classifier: Operating System :: OS Independent
Requires-Python: >=3.7
License-File: LICENSE
Dynamic: author
Dynamic: home-page
Dynamic: license-file
